pytwask/__init__.py
pytwask/config.py
pytwask/models.py
pytwask/auth/__init__.py
pytwask/auth/forms.py
pytwask/auth/views.py
pytwask/main/__init__.py
pytwask/main/views.py
pytwask/static/css/main.css
pytwask/static/css/normalize.css
pytwask/static/css/normalize.min.css
pytwask/static/js/main.js
pytwask/static/js/vendor/jquery-1.11.2.min.js
pytwask/static/js/vendor/modernizr-2.8.3-respond-1.4.2.min.js
pytwask/templates/400.html
pytwask/templates/403.html
pytwask/templates/404.html
pytwask/templates/500.html
pytwask/templates/base.html
pytwask/templates/form_macros.html
pytwask/templates/index.html
pytwask/templates/signup.html
pytwask/templates/timeline.html
pytwask/templates/tweets.html
pytwask/templates/user_history.html
pytwask/templates/user_settings.html
pytwask/tweets/__init__.py
pytwask/tweets/forms.py
pytwask/tweets/views.py
pytwask-0.2.3.data/scripts/autopytwask.py
pytwask-0.2.3.dist-info/METADATA
pytwask-0.2.3.dist-info/RECORD
pytwask-0.2.3.dist-info/WHEEL
pytwask-0.2.3.dist-info/top_level.txt
