Metadata-Version: 2.1
Name: pytwask
Version: 0.2.3
Summary: A twitter-toy-clone frontend using Python and Flask
Home-page: https://renweizhukov.github.io/pytwask
Author: Wei Ren
Author-email: renwei2004@gmail.com
License: UNKNOWN
Project-URL: Bug Reports, https://github.com/renweizhukov/pytwask/issues
Project-URL: Documentation, https://renweizhukov.github.io/pytwask
Project-URL: Source, https://github.com/renweizhukov/pytwask
Keywords: flask twitter python3.6
Platform: UNKNOWN
Classifier: Development Status :: 4 - Beta
Classifier: Intended Audience :: Developers
Classifier: Topic :: Internet :: WWW/HTTP :: WSGI :: Application
Classifier: License :: OSI Approved :: Apache Software License
Classifier: Programming Language :: Python :: 3.6
Requires-Python: >=3.6
Requires-Dist: Flask
Requires-Dist: Flask-DebugToolbar
Requires-Dist: Flask-Login
Requires-Dist: Flask-Moment
Requires-Dist: Flask-WTF
Requires-Dist: WTForms
Requires-Dist: itsdangerous
Requires-Dist: pytwis
Requires-Dist: setuptools
